setup.py
announce/__init__.py
announce/middleware.py
announce/templatetags/__init__.py
announce/templatetags/announcetags.py
django_announce.egg-info/PKG-INFO
django_announce.egg-info/SOURCES.txt
django_announce.egg-info/dependency_links.txt
django_announce.egg-info/top_level.txt