Metadata-Version: 1.0
Name: django-announce
Version: 0.1.0
Summary: an Announce.js client for Django
Home-page: http://github.com/ozkatz/django-announce/
Author: Oz Katz
Author-email: oz.katz@ripplify.com
License: BSD
Platform: UNKNOWN
Classifier: Development Status :: 3 - Alpha
Classifier: Environment :: Web Environment
Classifier: Intended Audience :: Developers
Classifier: License :: OSI Approved :: BSD License
Classifier: Operating System :: OS Independent
Classifier: Programming Language :: Python
Classifier: Framework :: Django
